mpy_kernel_upydevice/__init__.py
mpy_kernel_upydevice/__main__.py
mpy_kernel_upydevice/install.py
mpy_kernel_upydevice/jupyter_console_config.py
mpy_kernel_upydevice/kernel.py
mpy_kernel_upydevice/set_monokai.py
jupyter_micropython_upydevice-0.0.7.dist-info/LICENSE
jupyter_micropython_upydevice-0.0.7.dist-info/METADATA
jupyter_micropython_upydevice-0.0.7.dist-info/WHEEL
jupyter_micropython_upydevice-0.0.7.dist-info/top_level.txt
jupyter_micropython_upydevice-0.0.7.dist-info/RECORD
