Metadata-Version: 2.1
Name: jupyter-micropython-upydevice
Version: 0.0.7
Summary: Jupyter kernel based on upydevice for operating MicroPython
Home-page: https://github.com/Carglglz/jupyter_upydevice_kernel
Author: Carlos Gil Gonzalez
Author-email: carlosgilglez@gmail.com
License: GPL3
Keywords: jupyter micropython upydevice
Platform: UNKNOWN
Classifier: Development Status :: 3 - Alpha
Classifier: Intended Audience :: Developers
Classifier: Intended Audience :: Science/Research
Classifier: Intended Audience :: Education
Classifier: Operating System :: MacOS :: MacOS X
Classifier: Operating System :: POSIX :: Linux
Classifier: License :: OSI Approved :: MIT License
Classifier: Programming Language :: Python :: 3.6
Classifier: Programming Language :: Python :: 3.7
Classifier: Programming Language :: Python :: 3.8
Classifier: Topic :: System :: Monitoring
Classifier: Topic :: Scientific/Engineering
Classifier: Topic :: Software Development :: Embedded Systems
Classifier: Topic :: Terminals
Requires-Dist: upydevice (>=0.3.4)
